{"primary":{"value":"#00927a","type":"color","description":"green","rawValue":"#00927a"},"secondary":{"value":"#80d0c7","type":"color","description":"lgreen","rawValue":"#80d0c7"},"greyscale-light":{"value":"#fafafa","type":"color","description":"white","rawValue":"#fafafa"},"greyscale-light-grey":{"value":"#dfdfdf","type":"color","description":"lgrey","rawValue":"#dfdfdf"},"greyscale-dark-grey":{"value":"#859398","type":"color","description":"grey","rawValue":"#859398"},"greyscale-dark":{"value":"#0e111b","type":"color","description":"black","rawValue":"#0e111b"},"semantic-import":{"value":"#df5555","type":"color","description":"red","rawValue":"#df5555"},"bg-chat":{"value":"#fff8f84d","type":"color","description":"blossom","rawValue":"#fff8f84d"},"fontFamilies":{"suit":{"value":"SUIT","type":"fontFamilies","rawValue":"SUIT"}},"lineHeights":{"0":{"value":53,"type":"lineHeights","rawValue":"53"},"1":{"value":40,"type":"lineHeights","rawValue":"40"},"2":{"value":28,"type":"lineHeights","rawValue":"28"},"3":{"value":22,"type":"lineHeights","rawValue":"22"},"4":{"value":20,"type":"lineHeights","rawValue":"20"},"5":{"value":18,"type":"lineHeights","rawValue":"18"}},"fontSizes":{"caption":{"value":12,"type":"fontSizes","rawValue":"12"},"default":{"value":14,"type":"fontSizes","rawValue":"14"},"body2":{"value":16,"type":"fontSizes","rawValue":"16"},"body1":{"value":18,"type":"fontSizes","rawValue":"18"},"h3":{"value":24,"type":"fontSizes","rawValue":"24"},"h2":{"value":36,"type":"fontSizes","rawValue":"36"},"h1":{"value":48,"type":"fontSizes","rawValue":"48"}},"opacity15":{"value":15,"type":"opacity","description":"opacity for shadow","rawValue":"15"},"show":{"value":"true","type":"boolean","rawValue":"true"},"hide":{"value":"false","type":"boolean","rawValue":"false"},"states":{"disabled":{"value":"disabled","type":"State","rawValue":"disabled"},"default":{"value":"default","type":"State","rawValue":"default"},"hover":{"value":"hover","type":"State","rawValue":"hover"},"active":{"value":"active","type":"State","rawValue":"active"},"focus":{"value":"focus","type":"State","rawValue":"focus"}},"drop-shadow-lgrey-small":{"x":{"value":5,"type":"x"},"y":{"value":5,"type":"y"},"blur":{"value":10,"type":"blur"},"spread":{"value":0,"type":"spread"},"color":{"value":"#dfdfdf","type":"color"},"type":{"value":"dropShadow","type":"type"}},"drop-shadow-black":{"x":{"value":5,"type":"x"},"y":{"value":30,"type":"y"},"blur":{"value":30,"type":"blur"},"spread":{"value":0,"type":"spread"},"color":{"value":"#0e111b","type":"color"},"type":{"value":"dropShadow","type":"type"}},"padding":{"value":8,"type":"spacing","description":"default padding spacing","rawValue":"8"},"border-radius-xxs":{"value":5,"type":"borderRadius","rawValue":"{xxs}"},"border-radius-xs":{"value":15,"type":"borderRadius","rawValue":"{xs}"},"border-radius-s":{"value":20,"type":"borderRadius","rawValue":"{s}"},"border-radius-l":{"value":50,"type":"borderRadius","rawValue":"{l}"},"border-radius-xl":{"value":80,"type":"borderRadius","rawValue":"{xl}"},"border-radius-xxl":{"value":160,"type":"borderRadius","rawValue":"{xxl}"},"border-width":{"value":1,"type":"borderWidth","rawValue":"1"},"xxs":{"value":5,"type":"sizing","rawValue":"5"},"xs":{"value":15,"type":"sizing","rawValue":"15"},"s":{"value":20,"type":"sizing","rawValue":"20"},"l":{"value":50,"type":"sizing","rawValue":"50"},"xl":{"value":80,"type":"sizing","rawValue":"80"},"xxl":{"value":160,"type":"sizing","rawValue":"160"}}